ai_moderation/__init__.py
ai_moderation-0.0.1.dist-info/METADATA
ai_moderation-0.0.1.dist-info/WHEEL
ai_moderation-0.0.1.dist-info/RECORD
