Metadata-Version: 2.4
Name: ai-moderation
Version: 0.0.1
Summary: Whitecircle.ai moderation helpers for content safety and policy enforcement.
Author: White Circle
License: MIT
Keywords: ai,filters,moderation,policy,safety,whitecircle.ai
Classifier: Development Status :: 3 - Alpha
Classifier: License :: OSI Approved :: MIT License
Classifier: Programming Language :: Python :: 3
Requires-Python: >=3.9
